testteller/__init__.py
testteller/_version.py
testteller/config.py
testteller/main.py
testteller/automator_agent/__init__.py
testteller/automator_agent/application_context.py
testteller/automator_agent/base_generator.py
testteller/automator_agent/cli.py
testteller/automator_agent/rag_enhanced_generator.py
testteller/automator_agent/config/__init__.py
testteller/automator_agent/config/automation.py
testteller/automator_agent/parser/__init__.py
testteller/automator_agent/parser/markdown_parser.py
testteller/core/__init__.py
testteller/core/constants.py
testteller/core/config/__init__.py
testteller/core/config/config_wizard.py
testteller/core/config/ui.py
testteller/core/config/validators.py
testteller/core/config/wizard.py
testteller/core/config/writers.py
testteller/core/config/providers/__init__.py
testteller/core/config/providers/base.py
testteller/core/config/providers/claude.py
testteller/core/config/providers/gemini.py
testteller/core/config/providers/llama.py
testteller/core/config/providers/openai.py
testteller/core/data_ingestion/__init__.py
testteller/core/data_ingestion/code_loader.py
testteller/core/data_ingestion/document_loader.py
testteller/core/data_ingestion/text_splitter.py
testteller/core/data_ingestion/unified_document_parser.py
testteller/core/llm/__init__.py
testteller/core/llm/base_client.py
testteller/core/llm/claude_client.py
testteller/core/llm/gemini_client.py
testteller/core/llm/llama_client.py
testteller/core/llm/llm_manager.py
testteller/core/llm/openai_client.py
testteller/core/utils/__init__.py
testteller/core/utils/exceptions.py
testteller/core/utils/helpers.py
testteller/core/utils/loader.py
testteller/core/utils/retry_helpers.py
testteller/core/vector_store/__init__.py
testteller/core/vector_store/chromadb_manager.py
testteller/generator_agent/__init__.py
testteller/generator_agent/prompts.py
testteller/generator_agent/agent/__init__.py
testteller/generator_agent/agent/testteller_agent.py
testteller-2.0.3.dist-info/licenses/LICENSE
testteller-2.0.3.dist-info/licenses/NOTICE
testteller-2.0.3.dist-info/METADATA
testteller-2.0.3.dist-info/WHEEL
testteller-2.0.3.dist-info/entry_points.txt
testteller-2.0.3.dist-info/top_level.txt
testteller-2.0.3.dist-info/RECORD
