Metadata-Version: 2.4
Name: testteller
Version: 2.0.3
Summary: AI-Powered Test Agent for Test Case Generation and Automation using RAG & GenAI
Author: Aviral Nigam
License: Apache License 2.0
Keywords: testing,ai,rag,test-automation,code-generation,llm,pytest,qa,quality-assurance,test-cases,vector-store,chromadb,generative-ai,openai,anthropic,claude,gemini,junit,jest,testng,automation-framework
Classifier: Development Status :: 4 - Beta
Classifier: Intended Audience :: Developers
Classifier: Intended Audience :: Information Technology
Classifier: License :: OSI Approved :: Apache Software License
Classifier: Programming Language :: Python :: 3
Classifier: Programming Language :: Python :: 3.11
Classifier: Programming Language :: Python :: 3.12
Classifier: Programming Language :: Python :: 3.13
Classifier: Operating System :: OS Independent
Classifier: Topic :: Software Development :: Testing
Classifier: Topic :: Scientific/Engineering :: Artificial Intelligence
Requires-Python: >=3.11
License-File: LICENSE
License-File: NOTICE
Requires-Dist: google-generativeai>=0.3.0
Requires-Dist: chromadb>=0.4.0
Requires-Dist: langchain>=0.1.0
Requires-Dist: langchain-google-genai>=1.0.0
Requires-Dist: python-docx>=0.8.11
Requires-Dist: PyMuPDF>=1.23.0
Requires-Dist: openpyxl>=3.1.0
Requires-Dist: GitPython>=3.1.0
Requires-Dist: typer>=0.9.0
Requires-Dist: python-dotenv>=1.0.0
Requires-Dist: pydantic>=2.0.0
Requires-Dist: pydantic-settings>=2.0.0
Requires-Dist: tenacity>=8.0.0
Requires-Dist: python-json-logger>=2.0.0
Requires-Dist: tiktoken>=0.5.0
Requires-Dist: aiofiles>=23.0.0
Requires-Dist: openai>=1.0.0
Requires-Dist: anthropic>=0.8.0
Requires-Dist: httpx>=0.24.0
Requires-Dist: markdown>=3.5.0
Requires-Dist: weasyprint>=60.0
Provides-Extra: test
Requires-Dist: pytest>=7.0.0; extra == "test"
Requires-Dist: pytest-asyncio>=0.21.0; extra == "test"
Requires-Dist: pytest-cov>=4.0.0; extra == "test"
Requires-Dist: pytest-mock>=3.10.0; extra == "test"
Requires-Dist: pytest-timeout>=2.1.0; extra == "test"
Requires-Dist: pytest-xdist>=3.0.0; extra == "test"
Requires-Dist: coverage>=7.0.0; extra == "test"
Provides-Extra: dev
Requires-Dist: black>=23.0.0; extra == "dev"
Requires-Dist: isort>=5.12.0; extra == "dev"
Requires-Dist: flake8>=6.0.0; extra == "dev"
Requires-Dist: mypy>=1.5.0; extra == "dev"
Requires-Dist: pre-commit>=3.0.0; extra == "dev"
Provides-Extra: docs
Requires-Dist: mkdocs>=1.5.0; extra == "docs"
Requires-Dist: mkdocs-material>=9.0.0; extra == "docs"
Requires-Dist: mkdocstrings[python]>=0.23.0; extra == "docs"
Dynamic: license-file
